<annotation>
	<folder>American_Staffordshire_terrier</folder>
	<filename>9.jpg</filename>
	<path>D:\Aprendizaje Automático\Proyecto\Images\Images\Fio\n02093428-American_Staffordshire_terrier\American_Staffordshire_terrier\9.jpg</path>
	<source>
		<database>Unknown</database>
	</source>
	<size>
		<width>360</width>
		<height>256</height>
		<depth>3</depth>
	</size>
	<segmented>0</segmented>
	<object>
		<name>dog</name>
		<pose>Unspecified</pose>
		<truncated>0</truncated>
		<difficult>0</difficult>
		<bndbox>
			<xmin>16</xmin>
			<ymin>38</ymin>
			<xmax>314</xmax>
			<ymax>254</ymax>
		</bndbox>
	</object>
</annotation>
