<annotation>
	<folder>borzoi</folder>
	<filename>3.jpg</filename>
	<path>D:\Aprendizaje Automático\Proyecto\Images\Images\Fio\n02090622-borzoi\borzoi\3.jpg</path>
	<source>
		<database>Unknown</database>
	</source>
	<size>
		<width>336</width>
		<height>500</height>
		<depth>3</depth>
	</size>
	<segmented>0</segmented>
	<object>
		<name>dog</name>
		<pose>Unspecified</pose>
		<truncated>0</truncated>
		<difficult>0</difficult>
		<bndbox>
			<xmin>43</xmin>
			<ymin>46</ymin>
			<xmax>276</xmax>
			<ymax>483</ymax>
		</bndbox>
	</object>
</annotation>
